qss/__init__.py
qss/admm.py
qss/descent.py
qss/linearoperator.py
qss/matrix.py
qss/polish.py
qss/precondition.py
qss/proximal.py
qss/qss.py
qss/util.py
qss-0.2.4.dist-info/LICENSE
qss-0.2.4.dist-info/METADATA
qss-0.2.4.dist-info/WHEEL
qss-0.2.4.dist-info/top_level.txt
qss-0.2.4.dist-info/RECORD
