Metadata-Version: 2.1
Name: qss
Version: 0.2.4
Summary: QSS: Quadratic-Separable Solver
Author-email: Luke Volpatti <bennetm@stanford.edu>
Maintainer-email: Sara Miskovich <smiskov@slac.stanford.edu>
License: Apache License
Project-URL: Homepage, https://github.com/cvxgrp/qss
Project-URL: Bug Tracker, https://github.com/cvxgrp/qss/issues
Classifier: Development Status :: 4 - Beta
Classifier: License :: OSI Approved :: Apache Software License
Classifier: Programming Language :: Python :: 3 :: Only
Classifier: Programming Language :: Python :: 3.6
Classifier: Programming Language :: Python :: 3.7
Classifier: Programming Language :: Python :: 3.8
Classifier: Programming Language :: Python :: 3.9
Classifier: Programming Language :: Python :: 3.10
Classifier: Programming Language :: Python :: 3.11
Classifier: Programming Language :: Python :: 3.12
Classifier: Intended Audience :: Science/Research
Classifier: Topic :: Scientific/Engineering
Requires-Python: >=3.6
License-File: LICENSE
Requires-Dist: scipy ==1.13.1
Requires-Dist: numpy
Requires-Dist: cvxpy
Requires-Dist: qdldl
Requires-Dist: matplotlib
